pkit/__init__.py
pkit/__main__.py
pkit/cli.py
pkit/fix.py
pkit/reporter.py
pkit/scanner.py
pkit/storage.py
pkit/tracker.py
pkit/vulndb.py
pkit_cli-0.1.0.dist-info/licenses/LICENSE
pkit_cli-0.1.0.dist-info/METADATA
pkit_cli-0.1.0.dist-info/WHEEL
pkit_cli-0.1.0.dist-info/entry_points.txt
pkit_cli-0.1.0.dist-info/top_level.txt
pkit_cli-0.1.0.dist-info/RECORD
