Metadata-Version: 2.4
Name: pkit-cli
Version: 0.1.0
Summary: A simple CLI tool to snapshot, track, and scan installed Python packages.
Author-email: ReRa0 <adamkimkh@gmail.com>
License-Expression: MIT
Requires-Python: >=3.7
License-File: LICENSE
Requires-Dist: requests
Dynamic: license-file
